[{"pk": 22, "model": "auth.permission", "fields": {"codename": "add_logentry", "name": "Can add log entry", "content_type": 8}}, {"pk": 23, "model": "auth.permission", "fields": {"codename": "change_logentry", "name": "Can change log entry", "content_type": 8}}, {"pk": 24, "model": "auth.permission", "fields": {"codename": "delete_logentry", "name": "Can delete log entry", "content_type": 8}}, {"pk": 4, "model": "auth.permission", "fields": {"codename": "add_group", "name": "Can add group", "content_type": 2}}, {"pk": 10, "model": "auth.permission", "fields": {"codename": "add_message", "name": "Can add message", "content_type": 4}}, {"pk": 1, "model": "auth.permission", "fields": {"codename": "add_permission", "name": "Can add permission", "content_type": 1}}, {"pk": 7, "model": "auth.permission", "fields": {"codename": "add_user", "name": "Can add user", "content_type": 3}}, {"pk": 5, "model": "auth.permission", "fields": {"codename": "change_group", "name": "Can change group", "content_type": 2}}, {"pk": 11, "model": "auth.permission", "fields": {"codename": "change_message", "name": "Can change message", "content_type": 4}}, {"pk": 2, "model": "auth.permission", "fields": {"codename": "change_permission", "name": "Can change permission", "content_type": 1}}, {"pk": 8, "model": "auth.permission", "fields": {"codename": "change_user", "name": "Can change user", "content_type": 3}}, {"pk": 6, "model": "auth.permission", "fields": {"codename": "delete_group", "name": "Can delete group", "content_type": 2}}, {"pk": 12, "model": "auth.permission", "fields": {"codename": "delete_message", "name": "Can delete message", "content_type": 4}}, {"pk": 3, "model": "auth.permission", "fields": {"codename": "delete_permission", "name": "Can delete permission", "content_type": 1}}, {"pk": 9, "model": "auth.permission", "fields": {"codename": "delete_user", "name": "Can delete user", "content_type": 3}}, {"pk": 25, "model": "auth.permission", "fields": {"codename": "add_comment", "name": "Can add comment", "content_type": 9}}, {"pk": 29, "model": "auth.permission", "fields": {"codename": "add_commentflag", "name": "Can add comment flag", "content_type": 10}}, {"pk": 28, "model": "auth.permission", "fields": {"codename": "can_moderate", "name": "Can moderate comments", "content_type": 9}}, {"pk": 26, "model": "auth.permission", "fields": {"codename": "change_comment", "name": "Can change comment", "content_type": 9}}, {"pk": 30, "model": "auth.permission", "fields": {"codename": "change_commentflag", "name": "Can change comment flag", "content_type": 10}}, {"pk": 27, "model": "auth.permission", "fields": {"codename": "delete_comment", "name": "Can delete comment", "content_type": 9}}, {"pk": 31, "model": "auth.permission", "fields": {"codename": "delete_commentflag", "name": "Can delete comment flag", "content_type": 10}}, {"pk": 13, "model": "auth.permission", "fields": {"codename": "add_contenttype", "name": "Can add content type", "content_type": 5}}, {"pk": 14, "model": "auth.permission", "fields": {"codename": "change_contenttype", "name": "Can change content type", "content_type": 5}}, {"pk": 15, "model": "auth.permission", "fields": {"codename": "delete_contenttype", "name": "Can delete content type", "content_type": 5}}, {"pk": 32, "model": "auth.permission", "fields": {"codename": "add_club", "name": "Can add club", "content_type": 11}}, {"pk": 35, "model": "auth.permission", "fields": {"codename": "add_division", "name": "Can add division", "content_type": 12}}, {"pk": 59, "model": "auth.permission", "fields": {"codename": "add_event", "name": "Can add event", "content_type": 20}}, {"pk": 65, "model": "auth.permission", "fields": {"codename": "add_eventstats", "name": "Can add event stats", "content_type": 22}}, {"pk": 53, "model": "auth.permission", "fields": {"codename": "add_eventstatus", "name": "Can add event status", "content_type": 18}}, {"pk": 50, "model": "auth.permission", "fields": {"codename": "add_eventtype", "name": "Can add event type", "content_type": 17}}, {"pk": 62, "model": "auth.permission", "fields": {"codename": "add_parameter", "name": "Can add parameter", "content_type": 21}}, {"pk": 56, "model": "auth.permission", "fields": {"codename": "add_rink", "name": "Can add rink", "content_type": 19}}, {"pk": 38, "model": "auth.permission", "fields": {"codename": "add_season", "name": "Can add season", "content_type": 13}}, {"pk": 41, "model": "auth.permission", "fields": {"codename": "add_skilllevel", "name": "Can add skill level", "content_type": 14}}, {"pk": 44, "model": "auth.permission", "fields": {"codename": "add_team", "name": "Can add team", "content_type": 15}}, {"pk": 47, "model": "auth.permission", "fields": {"codename": "add_userprofile", "name": "Can add user profile", "content_type": 16}}, {"pk": 33, "model": "auth.permission", "fields": {"codename": "change_club", "name": "Can change club", "content_type": 11}}, {"pk": 36, "model": "auth.permission", "fields": {"codename": "change_division", "name": "Can change division", "content_type": 12}}, {"pk": 60, "model": "auth.permission", "fields": {"codename": "change_event", "name": "Can change event", "content_type": 20}}, {"pk": 66, "model": "auth.permission", "fields": {"codename": "change_eventstats", "name": "Can change event stats", "content_type": 22}}, {"pk": 54, "model": "auth.permission", "fields": {"codename": "change_eventstatus", "name": "Can change event status", "content_type": 18}}, {"pk": 51, "model": "auth.permission", "fields": {"codename": "change_eventtype", "name": "Can change event type", "content_type": 17}}, {"pk": 63, "model": "auth.permission", "fields": {"codename": "change_parameter", "name": "Can change parameter", "content_type": 21}}, {"pk": 57, "model": "auth.permission", "fields": {"codename": "change_rink", "name": "Can change rink", "content_type": 19}}, {"pk": 39, "model": "auth.permission", "fields": {"codename": "change_season", "name": "Can change season", "content_type": 13}}, {"pk": 42, "model": "auth.permission", "fields": {"codename": "change_skilllevel", "name": "Can change skill level", "content_type": 14}}, {"pk": 45, "model": "auth.permission", "fields": {"codename": "change_team", "name": "Can change team", "content_type": 15}}, {"pk": 48, "model": "auth.permission", "fields": {"codename": "change_userprofile", "name": "Can change user profile", "content_type": 16}}, {"pk": 34, "model": "auth.permission", "fields": {"codename": "delete_club", "name": "Can delete club", "content_type": 11}}, {"pk": 37, "model": "auth.permission", "fields": {"codename": "delete_division", "name": "Can delete division", "content_type": 12}}, {"pk": 61, "model": "auth.permission", "fields": {"codename": "delete_event", "name": "Can delete event", "content_type": 20}}, {"pk": 67, "model": "auth.permission", "fields": {"codename": "delete_eventstats", "name": "Can delete event stats", "content_type": 22}}, {"pk": 55, "model": "auth.permission", "fields": {"codename": "delete_eventstatus", "name": "Can delete event status", "content_type": 18}}, {"pk": 52, "model": "auth.permission", "fields": {"codename": "delete_eventtype", "name": "Can delete event type", "content_type": 17}}, {"pk": 64, "model": "auth.permission", "fields": {"codename": "delete_parameter", "name": "Can delete parameter", "content_type": 21}}, {"pk": 58, "model": "auth.permission", "fields": {"codename": "delete_rink", "name": "Can delete rink", "content_type": 19}}, {"pk": 40, "model": "auth.permission", "fields": {"codename": "delete_season", "name": "Can delete season", "content_type": 13}}, {"pk": 43, "model": "auth.permission", "fields": {"codename": "delete_skilllevel", "name": "Can delete skill level", "content_type": 14}}, {"pk": 46, "model": "auth.permission", "fields": {"codename": "delete_team", "name": "Can delete team", "content_type": 15}}, {"pk": 49, "model": "auth.permission", "fields": {"codename": "delete_userprofile", "name": "Can delete user profile", "content_type": 16}}, {"pk": 16, "model": "auth.permission", "fields": {"codename": "add_session", "name": "Can add session", "content_type": 6}}, {"pk": 17, "model": "auth.permission", "fields": {"codename": "change_session", "name": "Can change session", "content_type": 6}}, {"pk": 18, "model": "auth.permission", "fields": {"codename": "delete_session", "name": "Can delete session", "content_type": 6}}, {"pk": 19, "model": "auth.permission", "fields": {"codename": "add_site", "name": "Can add site", "content_type": 7}}, {"pk": 20, "model": "auth.permission", "fields": {"codename": "change_site", "name": "Can change site", "content_type": 7}}, {"pk": 21, "model": "auth.permission", "fields": {"codename": "delete_site", "name": "Can delete site", "content_type": 7}}, {"pk": 1, "model": "auth.group", "fields": {"name": "League Admins", "permissions": []}}, {"pk": 2, "model": "auth.group", "fields": {"name": "Club Admins", "permissions": []}}, {"pk": 3, "model": "auth.group", "fields": {"name": "Team Admins", "permissions": []}}, {"pk": 1, "model": "auth.user", "fields": {"username": "vsemenov", "first_name": "Vlad", "last_name": "Semenov", "is_active": true, "is_superuser": true, "is_staff": true, "last_login": "2009-09-18 01:48:08", "groups": [1], "user_permissions": [], "password": "sha1$e322a$c76ee4856bad23e3bebc9d5445aba9d6d0b3cf53", "email": "lothix@lothix.com", "date_joined": "2009-09-17 23:50:21"}}, {"pk": 2, "model": "auth.user", "fields": {"username": "leagueadmin", "first_name": "League", "last_name": "Admin", "is_active": true, "is_superuser": true, "is_staff": true, "last_login": "2009-09-18 01:49:39", "groups": [1], "user_permissions": [], "password": "sha1$f236c$b094fbfba5537eb77c40d804fed5827d26616cef", "email": "", "date_joined": "2009-09-18 01:27:46"}}, {"pk": 3, "model": "auth.user", "fields": {"username": "clubadmin", "first_name": "Club", "last_name": "Admin", "is_active": true, "is_superuser": false, "is_staff": true, "last_login": "2009-09-18 01:28:22", "groups": [2], "user_permissions": [], "password": "sha1$471a6$d5225e46ccc5a54dfdacdbd046df7e902f410ee2", "email": "", "date_joined": "2009-09-18 01:28:22"}}, {"pk": 4, "model": "auth.user", "fields": {"username": "teamadmin", "first_name": "Team", "last_name": "Admin", "is_active": true, "is_superuser": false, "is_staff": true, "last_login": "2009-09-18 01:28:47", "groups": [3], "user_permissions": [], "password": "sha1$1f0c5$a609c593ce734455842950acbf77e8e9a0f76f88", "email": "", "date_joined": "2009-09-18 01:28:47"}}]
